mnflow/mfda/cad/__init__.py
mnflow/mfda/cad/components/element.py
mnflow/mfda/cad/components/multichannel.py
mnflow/mfda/cad/components/utils.py
mnflow/mfda/cad/dld/__init__.py
mnflow/mfda/cad/dld/theme/__init__.py
mnflow/mfda/cad/dld/theme/block.py
mnflow/mfda/cad/dld/theme/condenser_sorter.py
mnflow/mfda/cad/dld/theme/core.py
mnflow/mfda/cad/dld/theme/multistage.py
mnflow/mfda/cad/dld/theme/sidewall.py
mnflow/mfda/cad/dld/utils/__init__.py
mnflow/mfda/cad/dld/utils/boundary_model.py
mnflow/mfda/cad/utils/__init__.py
mnflow/mfda/cad/utils/common.py
mnflow/mfda/cad/utils/decorators.py
mnflow/mfda/cad/utils/inspections.py
mnflow/mfda/cad/utils/operations.py
mnflow/mfda/cad/utils/shapes.py
mnflow/mfda/cad/visual/__init__.py
mnflow/mfda/cad/visual/vis_layout.py
mnflow-0.0.2.2.dist-info/licenses/LICENSE
mnflow-0.0.2.2.dist-info/METADATA
mnflow-0.0.2.2.dist-info/WHEEL
mnflow-0.0.2.2.dist-info/top_level.txt
mnflow-0.0.2.2.dist-info/RECORD
