Metadata-Version: 2.4
Name: mnflow
Version: 0.0.2.2
Summary: A package for micro/nanoflow
Author-email: Aryan Mehboudi <armehbdev@gmail.com>
Maintainer-email: Aryan Mehboudi <armehbdev@gmail.com>
License-Expression: AGPL-3.0-only
Project-URL: Homepage, https://github.com/am-0code1/mnflow
Project-URL: documentation, https://mnflow.readthedocs.io/en/latest/
Project-URL: repository, https://github.com/am-0code1/mnflow
Project-URL: Issues, https://github.com/am-0code1/mnflow/issues
Classifier: Programming Language :: Python :: 3
Classifier: Operating System :: OS Independent
Classifier: Development Status :: 5 - Production/Stable
Requires-Python: <3.13,>=3.8
License-File: LICENSE
Requires-Dist: klayout
Requires-Dist: numpy
Requires-Dist: scipy
Requires-Dist: pillow
Provides-Extra: plot
Requires-Dist: matplotlib; extra == "plot"
Provides-Extra: test
Requires-Dist: pytest>=5.0.0; extra == "test"
Requires-Dist: pytest-cov; extra == "test"
Provides-Extra: lint
Requires-Dist: black; extra == "lint"
Requires-Dist: flake8; extra == "lint"
Requires-Dist: isort; extra == "lint"
Requires-Dist: pre-commit; extra == "lint"
Provides-Extra: docs
Requires-Dist: sphinx; extra == "docs"
Requires-Dist: sphinx-rtd-theme; extra == "docs"
Requires-Dist: myst-nb; extra == "docs"
Requires-Dist: mnflow[plot]; extra == "docs"
Provides-Extra: jupyter
Requires-Dist: ipykernel; extra == "jupyter"
Provides-Extra: dev
Requires-Dist: build; extra == "dev"
Requires-Dist: wheel; extra == "dev"
Requires-Dist: twine; extra == "dev"
Requires-Dist: setuptools>=61.0; extra == "dev"
Requires-Dist: mnflow[jupyter]; extra == "dev"
Provides-Extra: dev-full
Requires-Dist: mnflow[dev,docs,jupyter,lint,test]; extra == "dev-full"
Provides-Extra: full
Requires-Dist: mnflow[plot]; extra == "full"
Provides-Extra: all
Requires-Dist: mnflow[dev_full,full]; extra == "all"
Dynamic: license-file
